[
    {
        "id": "197eb3b7fa0f4649",
        "filename": "19 MARCH.pdf",
        ",": "https://drive.google.com/file/d/1UccaoTXlufbaisj0gox1OTECmxgO5Vd3/view",
        "input_text": "Fecha de Emisión:\nORIGINAL\nLA ESPINA GABRIELA MERCEDES\nGral Deheza 1954 - Lanus, Buenos Aires\nPeríodo Facturado Desde:\nHasta:\nFecha de Vto. para el pago:\nCondición de venta:\nCondición frente al IVA:\nApellido y Nombre / Razón Social:\nDomicilio:\n22/06/2025\n22/06/2025\n22/06/2025\n22/06/2025\n27239697718\nCONS DE PROPIETARIOS MANSILLA 3762\nMansilla General 3762 - Capital Federal, Ciudad de Buenos\nAires\nOtros medios de pago electrónico\nCUIT:\nIngresos Brutos:\nFecha de Inicio de Actividades:\nPunto de Venta:\nComp. Nro:\n00001\n00000973\nDomicilio Comercial:\nRazón Social:\nASCENSORES MARCH\nCondición frente al IVA:\nFACTURA\nC\nCOD. 011\nResponsable Monotributo\nConsumidor Final\n27239697718\n01/08/2020\nCUIT: 30587107313\nCódigo\nProducto / Servicio\nCantidad\nU. Medida\nPrecio Unit.\n% Bonif\nImp. Bonif.\nSubtotal\nABONO DEL MES DE JUNIO DE\n2025\n1,00\nunidades\n193000,00\n193000,00\n0,00\n0,00\n0,00\n193000,00\n193000,00\nSubtotal: $\nImporte Otros Tributos: $\nImporte Total: $\nCAE N°:\nFecha de Vto. de CAE:\nComprobante Autorizado\nEsta Agencia no se responsabiliza por los datos ingresados en el detalle de la operación\n02/07/2025\n75258638652355\n\"ASCENSORES MARCH \"\nPág. 1/1\nFecha de Emisión:\nDUPLICADO\nLA ESPINA GABRIELA MERCEDES\nGral Deheza 1954 - Lanus, Buenos Aires\nPeríodo Facturado Desde:\nHasta:\nFecha de Vto. para el pago:\nCondición de venta:\nCondición frente al IVA:\nApellido y Nombre / Razón Social:\nDomicilio:\n22/06/2025\n22/06/2025\n22/06/2025\n22/06/2025\n27239697718\nCONS DE PROPIETARIOS MANSILLA 3762\nMansilla General 3762 - Capital Federal, Ciudad de Buenos\nAires\nOtros medios de pago electrónico\nCUIT:\nIngresos Brutos:\nFecha de Inicio de Actividades:\nPunto de Venta:\nComp. Nro:\n00001\n00000973\nDomicilio Comercial:\nRazón Social:\nASCENSORES MARCH\nCondición frente al IVA:\nFACTURA\nC\nCOD. 011\nResponsable Monotributo\nConsumidor Final\n27239697718\n01/08/2020\nCUIT: 30587107313\nCódigo\nProducto / Servicio\nCantidad\nU. Medida\nPrecio Unit.\n% Bonif\nImp. Bonif.\nSubtotal\nABONO DEL MES DE JUNIO DE\n2025\n1,00\nunidades\n193000,00\n193000,00\n0,00\n0,00\n0,00\n193000,00\n193000,00\nSubtotal: $\nImporte Otros Tributos: $\nImporte Total: $\nCAE N°:\nFecha de Vto. de CAE:\nComprobante Autorizado\nEsta Agencia no se responsabiliza por los datos ingresados en el detalle de la operación\n02/07/2025\n75258638652355\n\"ASCENSORES MARCH \"\nPág. 1/1\nFecha de Emisión:\nTRIPLICADO\nLA ESPINA GABRIELA MERCEDES\nGral Deheza 1954 - Lanus, Buenos Aires\nPeríodo Facturado Desde:\nHasta:\nFecha de Vto. para el pago:\nCondición de venta:\nCondición frente al IVA:\nApellido y Nombre / Razón Social:\nDomicilio:\n22/06/2025\n22/06/2025\n22/06/2025\n22/06/2025\n27239697718\nCONS DE PROPIETARIOS MANSILLA 3762\nMansilla General 3762 - Capital Federal, Ciudad de Buenos\nAires\nOtros medios de pago electrónico\nCUIT:\nIngresos Brutos:\nFecha de Inicio de Actividades:\nPunto de Venta:\nComp. Nro:\n00001\n00000973\nDomicilio Comercial:\nRazón Social:\nASCENSORES MARCH\nCondición frente al IVA:\nFACTURA\nC\nCOD. 011\nResponsable Monotributo\nConsumidor Final\n27239697718\n01/08/2020\nCUIT: 30587107313\nCódigo\nProducto / Servicio\nCantidad\nU. Medida\nPrecio Unit.\n% Bonif\nImp. Bonif.\nSubtotal\nABONO DEL MES DE JUNIO DE\n2025\n1,00\nunidades\n193000,00\n193000,00\n0,00\n0,00\n0,00\n193000,00\n193000,00\nSubtotal: $\nImporte Otros Tributos: $\nImporte Total: $\nCAE N°:\nFecha de Vto. de CAE:\nComprobante Autorizado\nEsta Agencia no se responsabiliza por los datos ingresados en el detalle de la operación\n02/07/2025\n75258638652355\n\"ASCENSORES MARCH \"\nPág. 1/1",
        "expected_json": {
            "Fecha": "22/06/2025" ,
            "CUITEmisor": "27239697718" ,
            "RazonSocialEmisor": "LA ESPINA GABRIELA MERCEDES" ,
            "PtoVenta": "00001" ,
            "NroFactura": "00000973" ,
            "Monto": "193000,00" ,
            "CUITReceptor": "30587107313" ,
            "RazonSocialReceptor": "CONS DE PROPIETARIOS MANSILLA 3762"
        }
    },
    {
        "id": "197eb3b7fa0f4649",
        "filename": "36 REDONDO.pdf",
        ",": "https://drive.google.com/file/d/1ZDeNrp-aozOO-axzFn6_Y9cxc9jYlTRu/view",
        "input_text": "Fecha de Emisión:\nORIGINAL\nREDONDO RUBEN  FERNANDO\nSanchez De Bustamante 444 Piso:7 Dpto:G\n- Ciudad de Buenos Aires\nPeríodo Facturado Desde:\nHasta:\nFecha de Vto. para el pago:\nCondición de venta:\nCondición frente al IVA:\nApellido y Nombre / Razón Social:\nDomicilio:\n05/05/2025\n25/05/2025\n25/05/2025\n05/05/2025\n20271934506\nCONSORCIO LAVALLE 482\nLavalle 482 - Capital Federal, Ciudad de Buenos Aires\nContado\nCUIT:\nIngresos Brutos:\nFecha de Inicio de Actividades:\nPunto de Venta:\nComp. Nro:\n00002\n00001982\nDomicilio Comercial:\nRazón Social:\nBIOTECNO SOLUCIONES EN GAS Y CALEFACCIÓN\nCondición frente al IVA:\nFACTURA\nC\nCOD. 011\nResponsable Monotributo\nConsumidor Final\n20271934506\n08/05/2019\nCUIT: 30568329054\nCódigo\nProducto / Servicio\nCantidad\nU. Medida\nPrecio Unit.\n% Bonif\nImp. Bonif.\nSubtotal\nInspección de instalación térmica:\nMAYO 2025\n1,00\nunidades\n50005,00\n50005,00\n0,00\n0,00\n0,00\n50005,00\n50005,00\nSubtotal: $\nImporte Otros Tributos: $\nImporte Total: $\nCAE N°:\nFecha de Vto. de CAE:\nComprobante Autorizado\nEsta Agencia no se responsabiliza por los datos ingresados en el detalle de la operación\n15/05/2025\n75186858120117\n\"Soluciones en Gas y calefacción\"\nPág. 1/1\nFecha de Emisión:\nDUPLICADO\nREDONDO RUBEN  FERNANDO\nSanchez De Bustamante 444 Piso:7 Dpto:G\n- Ciudad de Buenos Aires\nPeríodo Facturado Desde:\nHasta:\nFecha de Vto. para el pago:\nCondición de venta:\nCondición frente al IVA:\nApellido y Nombre / Razón Social:\nDomicilio:\n05/05/2025\n25/05/2025\n25/05/2025\n05/05/2025\n20271934506\nCONSORCIO LAVALLE 482\nLavalle 482 - Capital Federal, Ciudad de Buenos Aires\nContado\nCUIT:\nIngresos Brutos:\nFecha de Inicio de Actividades:\nPunto de Venta:\nComp. Nro:\n00002\n00001982\nDomicilio Comercial:\nRazón Social:\nBIOTECNO SOLUCIONES EN GAS Y CALEFACCIÓN\nCondición frente al IVA:\nFACTURA\nC\nCOD. 011\nResponsable Monotributo\nConsumidor Final\n20271934506\n08/05/2019\nCUIT: 30568329054\nCódigo\nProducto / Servicio\nCantidad\nU. Medida\nPrecio Unit.\n% Bonif\nImp. Bonif.\nSubtotal\nInspección de instalación térmica:\nMAYO 2025\n1,00\nunidades\n50005,00\n50005,00\n0,00\n0,00\n0,00\n50005,00\n50005,00\nSubtotal: $\nImporte Otros Tributos: $\nImporte Total: $\nCAE N°:\nFecha de Vto. de CAE:\nComprobante Autorizado\nEsta Agencia no se responsabiliza por los datos ingresados en el detalle de la operación\n15/05/2025\n75186858120117\n\"Soluciones en Gas y calefacción\"\nPág. 1/1\nFecha de Emisión:\nTRIPLICADO\nREDONDO RUBEN  FERNANDO\nSanchez De Bustamante 444 Piso:7 Dpto:G\n- Ciudad de Buenos Aires\nPeríodo Facturado Desde:\nHasta:\nFecha de Vto. para el pago:\nCondición de venta:\nCondición frente al IVA:\nApellido y Nombre / Razón Social:\nDomicilio:\n05/05/2025\n25/05/2025\n25/05/2025\n05/05/2025\n20271934506\nCONSORCIO LAVALLE 482\nLavalle 482 - Capital Federal, Ciudad de Buenos Aires\nContado\nCUIT:\nIngresos Brutos:\nFecha de Inicio de Actividades:\nPunto de Venta:\nComp. Nro:\n00002\n00001982\nDomicilio Comercial:\nRazón Social:\nBIOTECNO SOLUCIONES EN GAS Y CALEFACCIÓN\nCondición frente al IVA:\nFACTURA\nC\nCOD. 011\nResponsable Monotributo\nConsumidor Final\n20271934506\n08/05/2019\nCUIT: 30568329054\nCódigo\nProducto / Servicio\nCantidad\nU. Medida\nPrecio Unit.\n% Bonif\nImp. Bonif.\nSubtotal\nInspección de instalación térmica:\nMAYO 2025\n1,00\nunidades\n50005,00\n50005,00\n0,00\n0,00\n0,00\n50005,00\n50005,00\nSubtotal: $\nImporte Otros Tributos: $\nImporte Total: $\nCAE N°:\nFecha de Vto. de CAE:\nComprobante Autorizado\nEsta Agencia no se responsabiliza por los datos ingresados en el detalle de la operación\n15/05/2025\n75186858120117\n\"Soluciones en Gas y calefacción\"\nPág. 1/1",
        "expected_json": {
            "Fecha": "05/05/2025" ,
            "CUITEmisor": "20271934506" ,
            "RazonSocialEmisor": "REDONDO RUBEN FERNANDO" ,
            "PtoVenta": "00002" ,
            "NroFactura": "00001982" ,
            "Monto": "50005,00" ,
            "CUITReceptor": "30568329054" ,
            "RazonSocialReceptor": "CONSORCIO LAVALLE 482"
        }
    },
    {
        "id": "197eb3b7fa0f4649",
        "filename": "36 TOMAS ESQUIVEL ANTICIPO TERRAZA.pdf",
        ",": "https://drive.google.com/file/d/1Pha5M883CPnz0WC4yyuH2RpI3FAgoy4J/view",
        "input_text": "Fecha de Emisión:\nORIGINAL\nBAEZ SERGIO DIEGO\nPavon 1738 Piso:1 Dpto:1 - Ciudad de\nBuenos Aires\nPeríodo Facturado Desde:\nHasta:\nFecha de Vto. para el pago:\nCondición de venta:\nCondición frente al IVA:\nApellido y Nombre / Razón Social:\nDomicilio:\n22/05/2025\n22/05/2025\n22/05/2025\n22/05/2025\n20290889465\nCONSORCIO LAVALLE 482\nLavalle 482 - Capital Federal, Ciudad de Buenos Aires\nOtra\nCUIT:\nIngresos Brutos:\nFecha de Inicio de Actividades:\nPunto de Venta:\nComp. Nro:\n00002\n00000358\nDomicilio Comercial:\nRazón Social:\nBAEZ SERGIO DIEGO\nCondición frente al IVA:\nFACTURA\nC\nCOD. 011\nResponsable Monotributo\nConsumidor Final\nRegimen Simplificado\n01/05/2015\nCUIT: 30568329054\nCódigo\nProducto / Servicio\nCantidad\nU. Medida\nPrecio Unit.\n% Bonif\nImp. Bonif.\nSubtotal\n011\nLinpiesa y reparacion de terraza\nadelanto\n1,00\nunidades\n240000,00\n240000,00\n0,00\n0,00\n0,00\n240000,00\n240000,00\nSubtotal: $\nImporte Otros Tributos: $\nImporte Total: $\nCAE N°:\nFecha de Vto. de CAE:\nComprobante Autorizado\nEsta Agencia no se responsabiliza por los datos ingresados en el detalle de la operación\n01/06/2025\n75215976006178\nPág. 1/1\nFecha de Emisión:\nDUPLICADO\nBAEZ SERGIO DIEGO\nPavon 1738 Piso:1 Dpto:1 - Ciudad de\nBuenos Aires\nPeríodo Facturado Desde:\nHasta:\nFecha de Vto. para el pago:\nCondición de venta:\nCondición frente al IVA:\nApellido y Nombre / Razón Social:\nDomicilio:\n22/05/2025\n22/05/2025\n22/05/2025\n22/05/2025\n20290889465\nCONSORCIO LAVALLE 482\nLavalle 482 - Capital Federal, Ciudad de Buenos Aires\nOtra\nCUIT:\nIngresos Brutos:\nFecha de Inicio de Actividades:\nPunto de Venta:\nComp. Nro:\n00002\n00000358\nDomicilio Comercial:\nRazón Social:\nBAEZ SERGIO DIEGO\nCondición frente al IVA:\nFACTURA\nC\nCOD. 011\nResponsable Monotributo\nConsumidor Final\nRegimen Simplificado\n01/05/2015\nCUIT: 30568329054\nCódigo\nProducto / Servicio\nCantidad\nU. Medida\nPrecio Unit.\n% Bonif\nImp. Bonif.\nSubtotal\n011\nLinpiesa y reparacion de terraza\nadelanto\n1,00\nunidades\n240000,00\n240000,00\n0,00\n0,00\n0,00\n240000,00\n240000,00\nSubtotal: $\nImporte Otros Tributos: $\nImporte Total: $\nCAE N°:\nFecha de Vto. de CAE:\nComprobante Autorizado\nEsta Agencia no se responsabiliza por los datos ingresados en el detalle de la operación\n01/06/2025\n75215976006178\nPág. 1/1\nFecha de Emisión:\nTRIPLICADO\nBAEZ SERGIO DIEGO\nPavon 1738 Piso:1 Dpto:1 - Ciudad de\nBuenos Aires\nPeríodo Facturado Desde:\nHasta:\nFecha de Vto. para el pago:\nCondición de venta:\nCondición frente al IVA:\nApellido y Nombre / Razón Social:\nDomicilio:\n22/05/2025\n22/05/2025\n22/05/2025\n22/05/2025\n20290889465\nCONSORCIO LAVALLE 482\nLavalle 482 - Capital Federal, Ciudad de Buenos Aires\nOtra\nCUIT:\nIngresos Brutos:\nFecha de Inicio de Actividades:\nPunto de Venta:\nComp. Nro:\n00002\n00000358\nDomicilio Comercial:\nRazón Social:\nBAEZ SERGIO DIEGO\nCondición frente al IVA:\nFACTURA\nC\nCOD. 011\nResponsable Monotributo\nConsumidor Final\nRegimen Simplificado\n01/05/2015\nCUIT: 30568329054\nCódigo\nProducto / Servicio\nCantidad\nU. Medida\nPrecio Unit.\n% Bonif\nImp. Bonif.\nSubtotal\n011\nLinpiesa y reparacion de terraza\nadelanto\n1,00\nunidades\n240000,00\n240000,00\n0,00\n0,00\n0,00\n240000,00\n240000,00\nSubtotal: $\nImporte Otros Tributos: $\nImporte Total: $\nCAE N°:\nFecha de Vto. de CAE:\nComprobante Autorizado\nEsta Agencia no se responsabiliza por los datos ingresados en el detalle de la operación\n01/06/2025\n75215976006178\nPág. 1/1",
        "expected_json": {
            "Fecha": "22/05/2025" ,
            "CUITEmisor": "20290889465" ,
            "RazonSocialEmisor": "BAEZ SERGIO DIEGO" ,
            "PtoVenta": "00002" ,
            "NroFactura": "00000358" ,
            "Monto": "240000,00" ,
            "CUITReceptor": "30568329054" ,
            "RazonSocialReceptor": "CONSORCIO LAVALLE 482"
        }
    },
    {
        "id": "197eb3b7fa0f4649",
        "filename": "19 REYES FC982.pdf",
        ",": "https://drive.google.com/file/d/1WeKM69UPT6LNdco4BwLirKyaASbQIUkb/view",
        "input_text": "Fecha de Emisión:\nORIGINAL\nREYES JULIO RAFAEL\nSanchez De Loria 1139 Piso:14 Dpto:B -\nCiudad de Buenos Aires\nPeríodo Facturado Desde:\nHasta:\nFecha de Vto. para el pago:\nCondición de venta:\nCondición frente al IVA:\nApellido y Nombre / Razón Social:\nDomicilio:\n17/06/2025\n17/06/2025\n17/06/2025\n17/06/2025\n20921018585\nCONS DE PROPIETARIOS MANSILLA 3762\nMansilla General 3762 - Capital Federal, Ciudad de Buenos\nAires\nContado\nCUIT:\nIngresos Brutos:\nFecha de Inicio de Actividades:\nPunto de Venta:\nComp. Nro:\n00004\n00000982\nDomicilio Comercial:\nRazón Social:\nREYES JULIO RAFAEL\nCondición frente al IVA:\nFACTURA\nC\nCOD. 011\nResponsable Monotributo\nConsumidor Final\n813247-10\n01/01/1992\nCUIT: 30587107313\nCódigo\nProducto / Servicio\nCantidad\nU. Medida\nPrecio Unit.\n% Bonif\nImp. Bonif.\nSubtotal\nPor la medición anual de la puesta a\ntierra del edificio y protocolo de\nmedición, correspondiente al año\n2025.\n1,00\nunidades\n111200,00\n111200,00\n0,00\n0,00\n0,00\n111200,00\n111200,00\nSubtotal: $\nImporte Otros Tributos: $\nImporte Total: $\nCAE N°:\nFecha de Vto. de CAE:\nComprobante Autorizado\nEsta Agencia no se responsabiliza por los datos ingresados en el detalle de la operación\n27/06/2025\n75245163241403\n\"Técnico Mecánico Electricista - Mat. COPIME T010698 - Cel: 15-64757792\"\nPág. 1/1\nFecha de Emisión:\nDUPLICADO\nREYES JULIO RAFAEL\nSanchez De Loria 1139 Piso:14 Dpto:B -\nCiudad de Buenos Aires\nPeríodo Facturado Desde:\nHasta:\nFecha de Vto. para el pago:\nCondición de venta:\nCondición frente al IVA:\nApellido y Nombre / Razón Social:\nDomicilio:\n17/06/2025\n17/06/2025\n17/06/2025\n17/06/2025\n20921018585\nCONS DE PROPIETARIOS MANSILLA 3762\nMansilla General 3762 - Capital Federal, Ciudad de Buenos\nAires\nContado\nCUIT:\nIngresos Brutos:\nFecha de Inicio de Actividades:\nPunto de Venta:\nComp. Nro:\n00004\n00000982\nDomicilio Comercial:\nRazón Social:\nREYES JULIO RAFAEL\nCondición frente al IVA:\nFACTURA\nC\nCOD. 011\nResponsable Monotributo\nConsumidor Final\n813247-10\n01/01/1992\nCUIT: 30587107313\nCódigo\nProducto / Servicio\nCantidad\nU. Medida\nPrecio Unit.\n% Bonif\nImp. Bonif.\nSubtotal\nPor la medición anual de la puesta a\ntierra del edificio y protocolo de\nmedición, correspondiente al año\n2025.\n1,00\nunidades\n111200,00\n111200,00\n0,00\n0,00\n0,00\n111200,00\n111200,00\nSubtotal: $\nImporte Otros Tributos: $\nImporte Total: $\nCAE N°:\nFecha de Vto. de CAE:\nComprobante Autorizado\nEsta Agencia no se responsabiliza por los datos ingresados en el detalle de la operación\n27/06/2025\n75245163241403\n\"Técnico Mecánico Electricista - Mat. COPIME T010698 - Cel: 15-64757792\"\nPág. 1/1\nFecha de Emisión:\nTRIPLICADO\nREYES JULIO RAFAEL\nSanchez De Loria 1139 Piso:14 Dpto:B -\nCiudad de Buenos Aires\nPeríodo Facturado Desde:\nHasta:\nFecha de Vto. para el pago:\nCondición de venta:\nCondición frente al IVA:\nApellido y Nombre / Razón Social:\nDomicilio:\n17/06/2025\n17/06/2025\n17/06/2025\n17/06/2025\n20921018585\nCONS DE PROPIETARIOS MANSILLA 3762\nMansilla General 3762 - Capital Federal, Ciudad de Buenos\nAires\nContado\nCUIT:\nIngresos Brutos:\nFecha de Inicio de Actividades:\nPunto de Venta:\nComp. Nro:\n00004\n00000982\nDomicilio Comercial:\nRazón Social:\nREYES JULIO RAFAEL\nCondición frente al IVA:\nFACTURA\nC\nCOD. 011\nResponsable Monotributo\nConsumidor Final\n813247-10\n01/01/1992\nCUIT: 30587107313\nCódigo\nProducto / Servicio\nCantidad\nU. Medida\nPrecio Unit.\n% Bonif\nImp. Bonif.\nSubtotal\nPor la medición anual de la puesta a\ntierra del edificio y protocolo de\nmedición, correspondiente al año\n2025.\n1,00\nunidades\n111200,00\n111200,00\n0,00\n0,00\n0,00\n111200,00\n111200,00\nSubtotal: $\nImporte Otros Tributos: $\nImporte Total: $\nCAE N°:\nFecha de Vto. de CAE:\nComprobante Autorizado\nEsta Agencia no se responsabiliza por los datos ingresados en el detalle de la operación\n27/06/2025\n75245163241403\n\"Técnico Mecánico Electricista - Mat. COPIME T010698 - Cel: 15-64757792\"\nPág. 1/1",
        "expected_json": {
            "Fecha": "17/06/2025" ,
            "CUITEmisor": "20921018585" ,
            "RazonSocialEmisor": "REYES JULIO RAFAEL" ,
            "PtoVenta": "00004" ,
            "NroFactura": "00000982" ,
            "Monto": "111200,00" ,
            "CUITReceptor": "30587107313" ,
            "RazonSocialReceptor": "CONS DE PROPIETARIOS MANSILLA 3762"
        }
    },
    {
        "id": "197eb3b7fa0f4649",
        "filename": "36 ALFOMBRA LLUVIA.pdf",
        ",": "https://drive.google.com/file/d/1wj88mK-i4MGYYXBLaWuFzA2-X1YCPOoC/view",
        "input_text": "Cant.\nDescripción\nUnitario\nImporte\n14 CAMINO PROTECTOR POR METRO Herringbone 68 cm  \n$ 10.913,00\n$ 152.782,00\nRazón Social:\nRaul placido herrera\nCuenta:\nML-\nRPH2025-\nAY\nCUIT:\n34772795\nDirección:\nLa Valle 482 - San Nicolás - 1047 - Capital Federal\nCondición IVA: Consumidor Final\nDirección entrega:\n - Capital Federal \nCondición Venta:\nContado\nTeléfono:\nGracias por su compra.  Visitenos en www.exito.com.ar\n75209407800\n291\n27/05/2025\nCAE:\nGuiaID: 1784\nSubtotal:\nDto: %\nImp. Internos:\nTOTAL:\n$ 152.782,00\n0,000\nReg. Especiales:\nSubtotal:\n$ 152.782,00\n$ 0,00\n$ 0,00\n$ 0,00\n$ 152.782,00\nPowered by\nRégimen de Transparencia Fiscal al Consumidor (Ley 27.743)\nOtros Impuestos Nacionales Indirectos\nIVA Contenido\n26515,884\n0,000\nB00005-00005784\nB\nNúmero:\nFecha:\n17/05/2025\n06\nFactura\nIVA: \nCUIT:\nINGRESOS BRUTOS:\nINICIO ACTIVIDADES:\nResponsable Inscripto\n30710737939\n90130710737939\n08/10/2008\nEXITO DISEÑO ACTUAL S.A.\nRep. Arabe Siria 2557, Ciudad de Buenos Aires\n(11) 4831-7456\npalermo@exito.com.ar\nwww.exito.com.ar\n1 / 1",
        "expected_json": {
            "Fecha": "17/05/2025" ,
            "CUITEmisor": "30710737939" ,
            "RazonSocialEmisor": "EXITO DISEÑO ACTUAL S.A." ,
            "PtoVenta": "00005" ,
            "NroFactura": "00005784" ,
            "Monto": "152782,00" ,
            "CUITReceptor": "34772795" ,
            "RazonSocialReceptor": "Raul placido herrera"
        }
    },
    {
        "id": "197eb3b7fa0f4649",
        "filename": "76 W BUENO CAMBIO LLAVE LOSA RADIANTE 10ºA.pdf",
        ",": "https://drive.google.com/file/d/1QMZEL5Xpjd36-20wIVICZAZwKMfYUwO9/view",
        "input_text": "Fecha de Emisión:\nORIGINAL\nBUENO RODRIGO WALTER\nNavarro 5032 Dpto:A - Ciudad de Buenos\nAires\nPeríodo Facturado Desde:\nHasta:\nFecha de Vto. para el pago:\nCondición de venta:\nCondición frente al IVA:\nApellido y Nombre / Razón Social:\nDomicilio:\n23/06/2025\n23/06/2025\n23/06/2025\n23/06/2025\n20209463785\nCONSORCIO  DE  PROPIETARIOS  LARREA 10571059\nLarrea 1057 - Capital Federal, Ciudad de Buenos Aires\nContado\nCUIT:\nIngresos Brutos:\nFecha de Inicio de Actividades:\nPunto de Venta:\nComp. Nro:\n00001\n00000192\nDomicilio Comercial:\nRazón Social:\nBUENO RODRIGO WALTER\nCondición frente al IVA:\nFACTURA\nC\nCOD. 011\nResponsable Monotributo\nIVA Sujeto Exento\n20209463785\n03/11/2016\nCUIT: 30598584458\nCódigo\nProducto / Servicio\nCantidad\nU. Medida\nPrecio Unit.\n% Bonif\nImp. Bonif.\nSubtotal\nSe rompio pared de placard para\ncambio llave de regulacion losa\nradiante.-\n1,00\nunidades\n730000,00\n730000,00\n0,00\n0,00\n0,00\n730000,00\n730000,00\nSubtotal: $\nImporte Otros Tributos: $\nImporte Total: $\nCAE N°:\nFecha de Vto. de CAE:\nComprobante Autorizado\nEsta Agencia no se responsabiliza por los datos ingresados en el detalle de la operación\n03/07/2025\n75255698810987\nPág. 1/1\nFecha de Emisión:\nDUPLICADO\nBUENO RODRIGO WALTER\nNavarro 5032 Dpto:A - Ciudad de Buenos\nAires\nPeríodo Facturado Desde:\nHasta:\nFecha de Vto. para el pago:\nCondición de venta:\nCondición frente al IVA:\nApellido y Nombre / Razón Social:\nDomicilio:\n23/06/2025\n23/06/2025\n23/06/2025\n23/06/2025\n20209463785\nCONSORCIO  DE  PROPIETARIOS  LARREA 10571059\nLarrea 1057 - Capital Federal, Ciudad de Buenos Aires\nContado\nCUIT:\nIngresos Brutos:\nFecha de Inicio de Actividades:\nPunto de Venta:\nComp. Nro:\n00001\n00000192\nDomicilio Comercial:\nRazón Social:\nBUENO RODRIGO WALTER\nCondición frente al IVA:\nFACTURA\nC\nCOD. 011\nResponsable Monotributo\nIVA Sujeto Exento\n20209463785\n03/11/2016\nCUIT: 30598584458\nCódigo\nProducto / Servicio\nCantidad\nU. Medida\nPrecio Unit.\n% Bonif\nImp. Bonif.\nSubtotal\nSe rompio pared de placard para\ncambio llave de regulacion losa\nradiante.-\n1,00\nunidades\n730000,00\n730000,00\n0,00\n0,00\n0,00\n730000,00\n730000,00\nSubtotal: $\nImporte Otros Tributos: $\nImporte Total: $\nCAE N°:\nFecha de Vto. de CAE:\nComprobante Autorizado\nEsta Agencia no se responsabiliza por los datos ingresados en el detalle de la operación\n03/07/2025\n75255698810987\nPág. 1/1\nFecha de Emisión:\nTRIPLICADO\nBUENO RODRIGO WALTER\nNavarro 5032 Dpto:A - Ciudad de Buenos\nAires\nPeríodo Facturado Desde:\nHasta:\nFecha de Vto. para el pago:\nCondición de venta:\nCondición frente al IVA:\nApellido y Nombre / Razón Social:\nDomicilio:\n23/06/2025\n23/06/2025\n23/06/2025\n23/06/2025\n20209463785\nCONSORCIO  DE  PROPIETARIOS  LARREA 10571059\nLarrea 1057 - Capital Federal, Ciudad de Buenos Aires\nContado\nCUIT:\nIngresos Brutos:\nFecha de Inicio de Actividades:\nPunto de Venta:\nComp. Nro:\n00001\n00000192\nDomicilio Comercial:\nRazón Social:\nBUENO RODRIGO WALTER\nCondición frente al IVA:\nFACTURA\nC\nCOD. 011\nResponsable Monotributo\nIVA Sujeto Exento\n20209463785\n03/11/2016\nCUIT: 30598584458\nCódigo\nProducto / Servicio\nCantidad\nU. Medida\nPrecio Unit.\n% Bonif\nImp. Bonif.\nSubtotal\nSe rompio pared de placard para\ncambio llave de regulacion losa\nradiante.-\n1,00\nunidades\n730000,00\n730000,00\n0,00\n0,00\n0,00\n730000,00\n730000,00\nSubtotal: $\nImporte Otros Tributos: $\nImporte Total: $\nCAE N°:\nFecha de Vto. de CAE:\nComprobante Autorizado\nEsta Agencia no se responsabiliza por los datos ingresados en el detalle de la operación\n03/07/2025\n75255698810987\nPág. 1/1",
        "expected_json": {
            "Fecha": "23/06/2025" ,
            "CUITEmisor": "20209463785" ,
            "RazonSocialEmisor": "BUENO RODRIGO WALTER" ,
            "PtoVenta": "00001" ,
            "NroFactura": "00000192" ,
            "Monto": "730000,00" ,
            "CUITReceptor": "30598584458" ,
            "RazonSocialReceptor": "CONSORCIO DE PROPIETARIOS LARREA 10571059"
        }
    },
    {
        "id": "197eb3b7fa0f4649",
        "filename": "76 Silva pintura 3 A FC227.pdf",
        ",": "https://drive.google.com/file/d/1X5gXdtb1LZ6_MOe_VegIDz9jkBVPzmyM/view",
        "input_text": "Fecha de Emisión:\nORIGINAL\nSILVA ARMANDO JAVIER\nAsamblea 4770 - San Justo, Buenos Aires\nPeríodo Facturado Desde:\nHasta:\nFecha de Vto. para el pago:\nCondición de venta:\nCondición frente al IVA:\nApellido y Nombre / Razón Social:\nDomicilio:\n12/06/2025\n12/06/2025\n12/06/2025\n12/06/2025\n20943321109\nCONSORCIO  DE  PROPIETARIOS  LARREA 10571059\nLarrea 1057 - Capital Federal, Ciudad de Buenos Aires\nContado\nCUIT:\nIngresos Brutos:\nFecha de Inicio de Actividades:\nPunto de Venta:\nComp. Nro:\n00001\n00000227\nDomicilio Comercial:\nRazón Social:\nCondición frente al IVA:\nFACTURA\nC\nCOD. 011\nResponsable Monotributo\nConsumidor Final\n200000\n14/05/2020\nCUIT: 30598584458\nCódigo\nProducto / Servicio\nCantidad\nU. Medida\nPrecio Unit.\n% Bonif\nImp. Bonif.\nSubtotal\nTrabajo de pinturas piso 3 A\n1,00\nunidades\n240000,00\n240000,00\n0,00\n0,00\n0,00\n240000,00\n240000,00\nSubtotal: $\nImporte Otros Tributos: $\nImporte Total: $\nCAE N°:\nFecha de Vto. de CAE:\nComprobante Autorizado\nEsta Agencia no se responsabiliza por los datos ingresados en el detalle de la operación\n22/06/2025\n75249542305255\n\"Ajs\"\nPág. 1/1\nFecha de Emisión:\nDUPLICADO\nSILVA ARMANDO JAVIER\nAsamblea 4770 - San Justo, Buenos Aires\nPeríodo Facturado Desde:\nHasta:\nFecha de Vto. para el pago:\nCondición de venta:\nCondición frente al IVA:\nApellido y Nombre / Razón Social:\nDomicilio:\n12/06/2025\n12/06/2025\n12/06/2025\n12/06/2025\n20943321109\nCONSORCIO  DE  PROPIETARIOS  LARREA 10571059\nLarrea 1057 - Capital Federal, Ciudad de Buenos Aires\nContado\nCUIT:\nIngresos Brutos:\nFecha de Inicio de Actividades:\nPunto de Venta:\nComp. Nro:\n00001\n00000227\nDomicilio Comercial:\nRazón Social:\nCondición frente al IVA:\nFACTURA\nC\nCOD. 011\nResponsable Monotributo\nConsumidor Final\n200000\n14/05/2020\nCUIT: 30598584458\nCódigo\nProducto / Servicio\nCantidad\nU. Medida\nPrecio Unit.\n% Bonif\nImp. Bonif.\nSubtotal\nTrabajo de pinturas piso 3 A\n1,00\nunidades\n240000,00\n240000,00\n0,00\n0,00\n0,00\n240000,00\n240000,00\nSubtotal: $\nImporte Otros Tributos: $\nImporte Total: $\nCAE N°:\nFecha de Vto. de CAE:\nComprobante Autorizado\nEsta Agencia no se responsabiliza por los datos ingresados en el detalle de la operación\n22/06/2025\n75249542305255\n\"Ajs\"\nPág. 1/1\nFecha de Emisión:\nTRIPLICADO\nSILVA ARMANDO JAVIER\nAsamblea 4770 - San Justo, Buenos Aires\nPeríodo Facturado Desde:\nHasta:\nFecha de Vto. para el pago:\nCondición de venta:\nCondición frente al IVA:\nApellido y Nombre / Razón Social:\nDomicilio:\n12/06/2025\n12/06/2025\n12/06/2025\n12/06/2025\n20943321109\nCONSORCIO  DE  PROPIETARIOS  LARREA 10571059\nLarrea 1057 - Capital Federal, Ciudad de Buenos Aires\nContado\nCUIT:\nIngresos Brutos:\nFecha de Inicio de Actividades:\nPunto de Venta:\nComp. Nro:\n00001\n00000227\nDomicilio Comercial:\nRazón Social:\nCondición frente al IVA:\nFACTURA\nC\nCOD. 011\nResponsable Monotributo\nConsumidor Final\n200000\n14/05/2020\nCUIT: 30598584458\nCódigo\nProducto / Servicio\nCantidad\nU. Medida\nPrecio Unit.\n% Bonif\nImp. Bonif.\nSubtotal\nTrabajo de pinturas piso 3 A\n1,00\nunidades\n240000,00\n240000,00\n0,00\n0,00\n0,00\n240000,00\n240000,00\nSubtotal: $\nImporte Otros Tributos: $\nImporte Total: $\nCAE N°:\nFecha de Vto. de CAE:\nComprobante Autorizado\nEsta Agencia no se responsabiliza por los datos ingresados en el detalle de la operación\n22/06/2025\n75249542305255\n\"Ajs\"\nPág. 1/1",
        "expected_json": {
            "Fecha": "12/06/2025" ,
            "CUITEmisor": "20943321109" ,
            "RazonSocialEmisor": "SILVA ARMANDO JAVIER" ,
            "PtoVenta": "00001" ,
            "NroFactura": "00000227" ,
            "Monto": "240000,00" ,
            "CUITReceptor": "30598584458" ,
            "RazonSocialReceptor": "CONSORCIO DE PROPIETARIOS LARREA 10571059"
        }
    }
]